gurobi/__init__.py
gurobi/main.py
upygrage-0.0.3.dist-info/LICENSE
upygrage-0.0.3.dist-info/METADATA
upygrage-0.0.3.dist-info/WHEEL
upygrage-0.0.3.dist-info/top_level.txt
upygrage-0.0.3.dist-info/RECORD
