Metadata-Version: 2.1
Name: upygrage
Version: 0.0.3
Summary: Upgrades a range of python functionalities
Home-page: https://github.com/iamlucassantos/upygrade
Author: Lucas Vieira dos Santos
Author-email: lucas6eng@gmail.com
License: UNKNOWN
Project-URL: Bug Tracker, https://github.com/iamlucassantos/upygrade/issues
Platform: UNKNOWN
Classifier: Programming Language :: Python :: 3
Classifier: License :: OSI Approved :: MIT License
Classifier: Operating System :: OS Independent
Requires-Python: >=3.6
License-File: LICENSE
